{
    "items": [
        {
            "key": "selamlama",
            "value": "Hoşgeldiniz"
        },
        {
            "key": "hakkinda",
            "value": "Hakkında"
        },
        {
            "key": "oyun",
            "value": "Oyun"
        },
        {
            "key": "oyun_dili",
            "value": "Oyun Dili"
        },
        {
            "key": "kamera_sarsintisi",
            "value": "Kamera Sarsıntısı"
        },
        {
            "key": "kan_gosterimi",
            "value": "Kan Gösterimi"
        },
        {
            "key": "geri_don",
            "value": "Geri Dön"
        },
        {
            "key": "oyna",
            "value": "Oyna"
        },
        {
            "key": "cikis",
            "value": "Çıkış"
        },
        {
            "key": "secenekler",
            "value": "Seçenekler"
        },
        {
            "key": "grafik",
            "value": "Grafik"
        },
        {
            "key": "ses",
            "value": "Ses"
        },
        {
            "key": "oyun_muzikleri",
            "value": "Oyun Müzikleri"
        },
        {
            "key": "menu_muzigi",
            "value": "Menü Müziği"
        },
        {
            "key": "ses_efektleri",
            "value": "Ses Efektleri"
        },
        {
            "key": "ortam_sesleri",
            "value": "Ortam Sesleri"
        },
        {
            "key": "tus_atamalari",
            "value": "Tuş Atamaları"
        },
        {
            "key": "hareket",
            "value": "Hareket"
        },
        {
            "key": "zipla",
            "value": "Zıpla"
        },
        {
            "key": "egil",
            "value": "Eğil"
        },
        {
            "key": "atil",
            "value": "Atıl"
        },
        {
            "key": "cakil",
            "value": "Çakıl"
        },
        {
            "key": "sol_el",
            "value": "Sol El"
        },
        {
            "key": "sag_el",
            "value": "Sağ El"
        },
        {
            "key": "klavye",
            "value": "Klavye"
        },
        {
            "key": "kumanda",
            "value": "Kumanda"
        },
        {
            "key": "tus_sec",
            "value": "Bir Tuş Seçin"
        },
        {
            "key": "programlama",
            "value": "Programlama"
        },
        {
            "key": "gorsel_tasarim",
            "value": "Görsel Tasarım"
        },
        {
            "key": "yeniden_oyna",
            "value": "Yeniden Oyna"
        },
        {
            "key": "cozunurluk",
            "value": "Çözünürlük"
        },
        {
            "key": "post_processing",
            "value": "Post Processing"
        },
        {
            "key": "kumas_fizigi",
            "value": "Kumaş Fiziği"
        },
        {
            "key": "parcaciklar",
            "value": "Parçacıklar"
        },
        {
            "key": "puan",
            "value": "Puan"
        },
        {
            "key": "basla",
            "value": "Başla"
        },
        {
            "key": "duraklat",
            "value": "Duraklat"
        },
        {
            "key": "devam_et",
            "value": "Devam Et"
        },
        {
            "key": "oyun_bitti",
            "value": "Oyun Bitti"
        },
        {
            "key": "oyun_kazandin",
            "value": "Kazandınız"
        },
        {
            "key": "sure",
            "value": "Süre"
        },
        {
            "key": "seviye",
            "value": "Seviye"
        },
        {
            "key": "karakter",
            "value": "Karakter"
        },
        {
            "key": "yukleniyor",
            "value": "YÜKLENİYOR"
        },
        {
            "key": "yukleniyor_baslik",
            "value": "Gizemli Dojo'nun Derinliklerinde"
        },
        {
            "key": "yukleniyor_metin",
            "value": "Karanlık koridorlar ve gizemli odalarla dolu olan bu dojo, cesur kaşifler için bir meydan okuma sunuyor."
        }
    ]
}
